webdriver_manager/__init__.py
webdriver_manager/chrome.py
webdriver_manager/dispatch.py
webdriver_manager/firefox.py
webdriver_manager/microsoft.py
webdriver_manager/opera.py
webdriver_manager/config/__init__.py
webdriver_manager/config/meta.py
webdriver_manager/core/__init__.py
webdriver_manager/core/archive.py
webdriver_manager/core/config.py
webdriver_manager/core/constants.py
webdriver_manager/core/download_manager.py
webdriver_manager/core/driver.py
webdriver_manager/core/driver_cache.py
webdriver_manager/core/http.py
webdriver_manager/core/logger.py
webdriver_manager/core/manager.py
webdriver_manager/core/utils.py
webdriver_manager/drivers/__init__.py
webdriver_manager/drivers/chrome.py
webdriver_manager/drivers/edge.py
webdriver_manager/drivers/firefox.py
webdriver_manager/drivers/ie.py
webdriver_manager/drivers/opera.py
hf_webdriver_manager-0.2.1.dist-info/LICENSE
hf_webdriver_manager-0.2.1.dist-info/METADATA
hf_webdriver_manager-0.2.1.dist-info/WHEEL
hf_webdriver_manager-0.2.1.dist-info/top_level.txt
hf_webdriver_manager-0.2.1.dist-info/RECORD
