Metadata-Version: 2.1
Name: hf-webdriver-manager
Version: 0.2.1
Summary: Library provides the way to automatically manage drivers for different browsers.
Home-page: https://github.com/HansBug/hf_webdriver_manager
Author: HansBug
Author-email: hansbug@buaa.edu.cn
License: Apache License, Version 2.0
Keywords: testing,selenium,driver,test automation
Classifier: License :: OSI Approved :: Apache Software License
Classifier: Intended Audience :: Information Technology
Classifier: Intended Audience :: Developers
Classifier: License :: OSI Approved :: Apache Software License
Classifier: Programming Language :: Python
Classifier: Programming Language :: Python :: 3
Classifier: Programming Language :: Python :: 3.7
Classifier: Programming Language :: Python :: 3.8
Classifier: Programming Language :: Python :: 3.9
Classifier: Programming Language :: Python :: 3.10
Classifier: Programming Language :: Python :: 3.11
Classifier: Topic :: Software Development :: Libraries :: Python Modules
Classifier: Operating System :: Microsoft :: Windows
Classifier: Operating System :: POSIX
Classifier: Operating System :: Unix
Classifier: Operating System :: MacOS
Requires-Python: >=3.7
License-File: LICENSE
Requires-Dist: certifi (>=2022)
Requires-Dist: packaging (>=21)
Requires-Dist: python-dotenv (>=0.20.0)
Requires-Dist: requests (>=2.20)
Requires-Dist: tqdm (>=4.20)
Requires-Dist: hbutils (>=0.9.0)
Requires-Dist: pyparsing (>=3.0.0) ; python_full_version >= "3.6.8"
Requires-Dist: urllib3 (~=1.13) ; python_version >= "2.7" and python_version not in "3.0, 3.1, 3.2, 3.3, 3.4, 3.5"
Requires-Dist: idna (>=3.0) ; python_version >= "3.5"
Requires-Dist: charset-normalizer (>=2) ; python_version >= "3.6"
Provides-Extra: test
Requires-Dist: bump2version (>=1.0.1) ; extra == 'test'
Requires-Dist: certifi (>=2022.12.7) ; extra == 'test'
Requires-Dist: codecov (>=2.1.12) ; extra == 'test'
Requires-Dist: iniconfig (>=1.1.1) ; extra == 'test'
Requires-Dist: packaging (>=21.3) ; extra == 'test'
Requires-Dist: pybrowsers (>=0.5.1) ; extra == 'test'
Requires-Dist: pysocks (>=1.7.1) ; extra == 'test'
Requires-Dist: pytest (>=7.2.0) ; extra == 'test'
Requires-Dist: pytest-cov (>=4.0.0) ; extra == 'test'
Requires-Dist: pytest-xdist (>=3.0.2) ; extra == 'test'
Requires-Dist: requests (>=2.28.1) ; extra == 'test'
Requires-Dist: selenium (>=4.6.0) ; extra == 'test'
Requires-Dist: sortedcontainers (>=2.4.0) ; extra == 'test'
Requires-Dist: execnet (>=1.9.0) ; (python_version >= "2.7" and python_version not in "3.0, 3.1, 3.2, 3.3, 3.4") and extra == 'test'
Requires-Dist: urllib3 (>=1.26.13) ; (python_version >= "2.7" and python_version not in "3.0, 3.1, 3.2, 3.3, 3.4, 3.5") and extra == 'test'
Requires-Dist: async-generator (>=1.10) ; (python_version >= "3.5") and extra == 'test'
Requires-Dist: attrs (>=22.1.0) ; (python_version >= "3.5") and extra == 'test'
Requires-Dist: idna (>=3.4) ; (python_version >= "3.5") and extra == 'test'
Requires-Dist: trio-websocket (>=0.9.2) ; (python_version >= "3.5") and extra == 'test'
Requires-Dist: charset-normalizer (>=2.1.1) ; (python_version >= "3.6") and extra == 'test'
Requires-Dist: pluggy (>=1.0.0) ; (python_version >= "3.6") and extra == 'test'
Requires-Dist: coverage (>=6.5.0) ; (python_version >= "3.7") and extra == 'test'
Requires-Dist: h11 (>=0.14.0) ; (python_version >= "3.7") and extra == 'test'
Requires-Dist: outcome (>=1.2.0) ; (python_version >= "3.7") and extra == 'test'
Requires-Dist: sniffio (>=1.3.0) ; (python_version >= "3.7") and extra == 'test'
Requires-Dist: trio (>=0.22.0) ; (python_version >= "3.7") and extra == 'test'
Requires-Dist: wsproto (>=1.2.0) ; (python_version >= "3.7") and extra == 'test'
Requires-Dist: pyxdg (>=0.28) ; (sys_platform == "linux") and extra == 'test'
